{
  "project_info": {
    "project_number": "524033716419",
    "project_id": "testsnslogin-308c1",
    "storage_bucket": "testsnslogin-308c1.appspot.com"
  },
  "client": [
    {
      "client_info": {
        "mobilesdk_app_id": "1:524033716419:android:b2cf45de56f22cbc0cf276",
        "android_client_info": {
          "package_name": "com.example.jongseong"
        }
      },
      "oauth_client": [
        {
          "client_id": "524033716419-vtpci0utoolvnafk5aus5qa59tejs4se.apps.googleusercontent.com",
          "client_type": 3
        }
      ],
      "api_key": [
        {
          "current_key": "AIzaSyDNKjzsN2ZZHULcfqx-Y_3i_n82L59JOwo"
        }
      ],
      "services": {
        "appinvite_service": {
          "other_platform_oauth_client": [
            {
              "client_id": "524033716419-vtpci0utoolvnafk5aus5qa59tejs4se.apps.googleusercontent.com",
              "client_type": 3
            },
            {
              "client_id": "524033716419-8416hfduanas1ug4crhd0e9ob71f0rej.apps.googleusercontent.com",
              "client_type": 2,
              "ios_info": {
                "bundle_id": "com.example.jongseong"
              }
            }
          ]
        }
      }
    }
  ],
  "configuration_version": "1"
}